[
  {
    "slug": "cotoov",
    "platform": "kick",
    "live": false,
    "viewers": 0,
    "thumb": null,
    "updatedAt": "2025-12-18T21:45:10.387Z",
    "error": "HTTP 403"
  },
  {
    "slug": "exequiel",
    "platform": "kick",
    "live": false,
    "viewers": 0,
    "thumb": null,
    "updatedAt": "2025-12-18T21:45:10.389Z",
    "error": "HTTP 403"
  },
  {
    "slug": "ciro",
    "platform": "kick",
    "live": false,
    "viewers": 0,
    "thumb": null,
    "updatedAt": "2025-12-18T21:45:10.412Z",
    "error": "HTTP 403"
  },
  {
    "slug": "jwaken",
    "platform": "kick",
    "live": false,
    "viewers": 0,
    "thumb": null,
    "updatedAt": "2025-12-18T21:45:10.420Z",
    "error": "HTTP 403"
  },
  {
    "slug": "ogsantiago",
    "platform": "kick",
    "live": false,
    "viewers": 0,
    "thumb": null,
    "updatedAt": "2025-12-18T21:45:10.458Z",
    "error": "HTTP 403"
  },
  {
    "slug": "zerok",
    "platform": "kick",
    "live": false,
    "viewers": 0,
    "thumb": null,
    "updatedAt": "2025-12-18T21:45:12.235Z",
    "error": "HTTP 403"
  },
  {
    "slug": "yxnsi",
    "platform": "kick",
    "live": false,
    "viewers": 0,
    "thumb": null,
    "updatedAt": "2025-12-18T21:45:12.263Z",
    "error": "HTTP 403"
  },
  {
    "slug": "tatog2",
    "platform": "kick",
    "live": false,
    "viewers": 0,
    "thumb": null,
    "updatedAt": "2025-12-18T21:45:12.276Z",
    "error": "HTTP 403"
  },
  {
    "slug": "peppalex",
    "platform": "kick",
    "live": false,
    "viewers": 0,
    "thumb": null,
    "updatedAt": "2025-12-18T21:45:12.303Z",
    "error": "HTTP 403"
  },
  {
    "slug": "jeyciiv",
    "platform": "kick",
    "live": false,
    "viewers": 0,
    "thumb": null,
    "updatedAt": "2025-12-18T21:45:12.309Z",
    "error": "HTTP 403"
  },
  {
    "slug": "fachitazz",
    "platform": "kick",
    "live": false,
    "viewers": 0,
    "thumb": null,
    "updatedAt": "2025-12-18T21:45:14.125Z",
    "error": "HTTP 403"
  },
  {
    "slug": "maiston",
    "platform": "kick",
    "live": false,
    "viewers": 0,
    "thumb": null,
    "updatedAt": "2025-12-18T21:45:14.129Z",
    "error": "HTTP 403"
  },
  {
    "slug": "ignaa",
    "platform": "kick",
    "live": false,
    "viewers": 0,
    "thumb": null,
    "updatedAt": "2025-12-18T21:45:14.145Z",
    "error": "HTTP 403"
  },
  {
    "slug": "viasuss",
    "platform": "kick",
    "live": false,
    "viewers": 0,
    "thumb": null,
    "updatedAt": "2025-12-18T21:45:14.164Z",
    "error": "HTTP 403"
  },
  {
    "slug": "joeelvzla",
    "platform": "kick",
    "live": false,
    "viewers": 0,
    "thumb": null,
    "updatedAt": "2025-12-18T21:45:14.170Z",
    "error": "HTTP 403"
  },
  {
    "slug": "trotadovzla",
    "platform": "kick",
    "live": false,
    "viewers": 0,
    "thumb": null,
    "updatedAt": "2025-12-18T21:45:15.970Z",
    "error": "HTTP 403"
  },
  {
    "slug": "bressser",
    "platform": "kick",
    "live": false,
    "viewers": 0,
    "thumb": null,
    "updatedAt": "2025-12-18T21:45:16.011Z",
    "error": "HTTP 403"
  },
  {
    "slug": "leiluchy",
    "platform": "kick",
    "live": false,
    "viewers": 0,
    "thumb": null,
    "updatedAt": "2025-12-18T21:45:16.012Z",
    "error": "HTTP 403"
  },
  {
    "slug": "icarito0o",
    "platform": "kick",
    "live": false,
    "viewers": 0,
    "thumb": null,
    "updatedAt": "2025-12-18T21:45:16.037Z",
    "error": "HTTP 403"
  },
  {
    "slug": "gangii",
    "platform": "kick",
    "live": false,
    "viewers": 0,
    "thumb": null,
    "updatedAt": "2025-12-18T21:45:16.050Z",
    "error": "HTTP 403"
  },
  {
    "slug": "magmaparalasnenas",
    "platform": "kick",
    "live": false,
    "viewers": 0,
    "thumb": null,
    "updatedAt": "2025-12-18T21:45:17.805Z",
    "error": "HTTP 403"
  }
]