[
  {
    "slug": "exequiel",
    "platform": "kick",
    "live": false,
    "viewers": 0,
    "thumb": null,
    "updatedAt": "2025-12-13T02:57:19.886Z",
    "error": "HTTP 403"
  },
  {
    "slug": "jwaken",
    "platform": "kick",
    "live": false,
    "viewers": 0,
    "thumb": null,
    "updatedAt": "2025-12-13T02:57:19.898Z",
    "error": "HTTP 403"
  },
  {
    "slug": "ogsantiago",
    "platform": "kick",
    "live": false,
    "viewers": 0,
    "thumb": null,
    "updatedAt": "2025-12-13T02:57:19.902Z",
    "error": "HTTP 403"
  },
  {
    "slug": "ciro",
    "platform": "kick",
    "live": false,
    "viewers": 0,
    "thumb": null,
    "updatedAt": "2025-12-13T02:57:19.903Z",
    "error": "HTTP 403"
  },
  {
    "slug": "cotoov",
    "platform": "kick",
    "live": false,
    "viewers": 0,
    "thumb": null,
    "updatedAt": "2025-12-13T02:57:19.913Z",
    "error": "HTTP 403"
  },
  {
    "slug": "zerok",
    "platform": "kick",
    "live": false,
    "viewers": 0,
    "thumb": null,
    "updatedAt": "2025-12-13T02:57:21.717Z",
    "error": "HTTP 403"
  },
  {
    "slug": "yxnsi",
    "platform": "kick",
    "live": false,
    "viewers": 0,
    "thumb": null,
    "updatedAt": "2025-12-13T02:57:21.734Z",
    "error": "HTTP 403"
  },
  {
    "slug": "peppalex",
    "platform": "kick",
    "live": false,
    "viewers": 0,
    "thumb": null,
    "updatedAt": "2025-12-13T02:57:21.742Z",
    "error": "HTTP 403"
  },
  {
    "slug": "tatog2",
    "platform": "kick",
    "live": false,
    "viewers": 0,
    "thumb": null,
    "updatedAt": "2025-12-13T02:57:21.746Z",
    "error": "HTTP 403"
  },
  {
    "slug": "jeyciiv",
    "platform": "kick",
    "live": false,
    "viewers": 0,
    "thumb": null,
    "updatedAt": "2025-12-13T02:57:21.752Z",
    "error": "HTTP 403"
  },
  {
    "slug": "maiston",
    "platform": "kick",
    "live": false,
    "viewers": 0,
    "thumb": null,
    "updatedAt": "2025-12-13T02:57:23.549Z",
    "error": "HTTP 403"
  },
  {
    "slug": "joeelvzla",
    "platform": "kick",
    "live": false,
    "viewers": 0,
    "thumb": null,
    "updatedAt": "2025-12-13T02:57:23.570Z",
    "error": "HTTP 403"
  },
  {
    "slug": "ignaa",
    "platform": "kick",
    "live": false,
    "viewers": 0,
    "thumb": null,
    "updatedAt": "2025-12-13T02:57:23.577Z",
    "error": "HTTP 403"
  },
  {
    "slug": "fachitazz",
    "platform": "kick",
    "live": false,
    "viewers": 0,
    "thumb": null,
    "updatedAt": "2025-12-13T02:57:23.587Z",
    "error": "HTTP 403"
  },
  {
    "slug": "viasuss",
    "platform": "kick",
    "live": false,
    "viewers": 0,
    "thumb": null,
    "updatedAt": "2025-12-13T02:57:23.597Z",
    "error": "HTTP 403"
  },
  {
    "slug": "leiluchy",
    "platform": "kick",
    "live": false,
    "viewers": 0,
    "thumb": null,
    "updatedAt": "2025-12-13T02:57:25.385Z",
    "error": "HTTP 403"
  },
  {
    "slug": "icarito0o",
    "platform": "kick",
    "live": false,
    "viewers": 0,
    "thumb": null,
    "updatedAt": "2025-12-13T02:57:25.414Z",
    "error": "HTTP 403"
  },
  {
    "slug": "trotadovzla",
    "platform": "kick",
    "live": false,
    "viewers": 0,
    "thumb": null,
    "updatedAt": "2025-12-13T02:57:25.417Z",
    "error": "HTTP 403"
  },
  {
    "slug": "gangii",
    "platform": "kick",
    "live": false,
    "viewers": 0,
    "thumb": null,
    "updatedAt": "2025-12-13T02:57:25.428Z",
    "error": "HTTP 403"
  },
  {
    "slug": "bressser",
    "platform": "kick",
    "live": false,
    "viewers": 0,
    "thumb": null,
    "updatedAt": "2025-12-13T02:57:25.432Z",
    "error": "HTTP 403"
  },
  {
    "slug": "magmaparalasnenas",
    "platform": "kick",
    "live": false,
    "viewers": 0,
    "thumb": null,
    "updatedAt": "2025-12-13T02:57:27.236Z",
    "error": "HTTP 403"
  }
]