[
  {
    "slug": "jwaken",
    "platform": "kick",
    "live": true,
    "viewers": 0,
    "thumb": null,
    "updatedAt": "2025-10-21T19:20:59.372Z"
  },
  {
    "slug": "zerok",
    "platform": "kick",
    "live": true,
    "viewers": 0,
    "thumb": "https://stream.kick.com/thumbnails/livestream/79848480/thumb0/video_thumbnail/thumb0.jpg",
    "updatedAt": "2025-10-21T19:20:59.421Z"
  },
  {
    "slug": "exequiel",
    "platform": "kick",
    "live": true,
    "viewers": 0,
    "thumb": "https://stream.kick.com/thumbnails/livestream/79846893/thumb0/video_thumbnail/thumb0.jpg",
    "updatedAt": "2025-10-21T19:20:59.445Z"
  },
  {
    "slug": "ogsantiago",
    "platform": "kick",
    "live": false,
    "viewers": 0,
    "thumb": null,
    "updatedAt": "2025-10-21T19:20:59.460Z"
  },
  {
    "slug": "cotoov",
    "platform": "kick",
    "live": false,
    "viewers": 0,
    "thumb": null,
    "updatedAt": "2025-10-21T19:20:59.553Z"
  },
  {
    "slug": "ciro",
    "platform": "kick",
    "live": false,
    "viewers": 0,
    "thumb": null,
    "updatedAt": "2025-10-21T19:20:59.575Z"
  },
  {
    "slug": "jeyciiv",
    "platform": "kick",
    "live": false,
    "viewers": 0,
    "thumb": null,
    "updatedAt": "2025-10-21T19:20:59.790Z"
  },
  {
    "slug": "yxnsi",
    "platform": "kick",
    "live": false,
    "viewers": 0,
    "thumb": null,
    "updatedAt": "2025-10-21T19:20:59.795Z"
  },
  {
    "slug": "tatog2",
    "platform": "kick",
    "live": false,
    "viewers": 0,
    "thumb": null,
    "updatedAt": "2025-10-21T19:20:59.805Z"
  },
  {
    "slug": "maiston",
    "platform": "kick",
    "live": false,
    "viewers": 0,
    "thumb": null,
    "updatedAt": "2025-10-21T19:20:59.886Z"
  },
  {
    "slug": "joeelvzla",
    "platform": "kick",
    "live": false,
    "viewers": 0,
    "thumb": null,
    "updatedAt": "2025-10-21T19:21:00.112Z"
  },
  {
    "slug": "peppalex",
    "platform": "kick",
    "live": false,
    "viewers": 0,
    "thumb": null,
    "updatedAt": "2025-10-21T19:21:00.194Z"
  },
  {
    "slug": "fachitazz",
    "platform": "kick",
    "live": false,
    "viewers": 0,
    "thumb": null,
    "updatedAt": "2025-10-21T19:21:00.289Z"
  },
  {
    "slug": "ignaa",
    "platform": "kick",
    "live": false,
    "viewers": 0,
    "thumb": null,
    "updatedAt": "2025-10-21T19:21:00.338Z"
  },
  {
    "slug": "viasuss",
    "platform": "kick",
    "live": false,
    "viewers": 0,
    "thumb": null,
    "updatedAt": "2025-10-21T19:21:00.403Z"
  },
  {
    "slug": "leiluchy",
    "platform": "kick",
    "live": false,
    "viewers": 0,
    "thumb": null,
    "updatedAt": "2025-10-21T19:21:00.407Z"
  },
  {
    "slug": "bressser",
    "platform": "kick",
    "live": false,
    "viewers": 0,
    "thumb": null,
    "updatedAt": "2025-10-21T19:21:00.838Z"
  },
  {
    "slug": "icarito0o",
    "platform": "kick",
    "live": false,
    "viewers": 0,
    "thumb": null,
    "updatedAt": "2025-10-21T19:21:00.843Z"
  },
  {
    "slug": "magmaparalasnenas",
    "platform": "kick",
    "live": false,
    "viewers": 0,
    "thumb": null,
    "updatedAt": "2025-10-21T19:21:00.851Z"
  },
  {
    "slug": "trotadovzla",
    "platform": "kick",
    "live": false,
    "viewers": 0,
    "thumb": null,
    "updatedAt": "2025-10-21T19:21:00.890Z"
  },
  {
    "slug": "gangii",
    "platform": "kick",
    "live": false,
    "viewers": 0,
    "thumb": null,
    "updatedAt": "2025-10-21T19:21:00.911Z"
  }
]