[
  {
    "slug": "jwaken",
    "platform": "kick",
    "live": false,
    "viewers": 0,
    "thumb": null,
    "updatedAt": "2025-10-16T15:18:10.490Z"
  },
  {
    "slug": "ogsantiago",
    "platform": "kick",
    "live": false,
    "viewers": 0,
    "thumb": null,
    "updatedAt": "2025-10-16T15:18:10.729Z"
  },
  {
    "slug": "exequiel",
    "platform": "kick",
    "live": false,
    "viewers": 0,
    "thumb": null,
    "updatedAt": "2025-10-16T15:18:10.733Z"
  },
  {
    "slug": "ciro",
    "platform": "kick",
    "live": false,
    "viewers": 0,
    "thumb": null,
    "updatedAt": "2025-10-16T15:18:10.811Z"
  },
  {
    "slug": "cotoov",
    "platform": "kick",
    "live": false,
    "viewers": 0,
    "thumb": null,
    "updatedAt": "2025-10-16T15:18:10.828Z"
  },
  {
    "slug": "tatog2",
    "platform": "kick",
    "live": false,
    "viewers": 0,
    "thumb": null,
    "updatedAt": "2025-10-16T15:18:11.070Z"
  },
  {
    "slug": "yxnsi",
    "platform": "kick",
    "live": false,
    "viewers": 0,
    "thumb": null,
    "updatedAt": "2025-10-16T15:18:11.112Z"
  },
  {
    "slug": "zerok",
    "platform": "kick",
    "live": false,
    "viewers": 0,
    "thumb": null,
    "updatedAt": "2025-10-16T15:18:11.136Z"
  },
  {
    "slug": "jeyciiv",
    "platform": "kick",
    "live": false,
    "viewers": 0,
    "thumb": null,
    "updatedAt": "2025-10-16T15:18:11.146Z"
  },
  {
    "slug": "maiston",
    "platform": "kick",
    "live": false,
    "viewers": 0,
    "thumb": null,
    "updatedAt": "2025-10-16T15:18:11.445Z"
  },
  {
    "slug": "joeelvzla",
    "platform": "kick",
    "live": false,
    "viewers": 0,
    "thumb": null,
    "updatedAt": "2025-10-16T15:18:11.491Z"
  },
  {
    "slug": "peppalex",
    "platform": "kick",
    "live": false,
    "viewers": 0,
    "thumb": null,
    "updatedAt": "2025-10-16T15:18:11.506Z"
  },
  {
    "slug": "ignaa",
    "platform": "kick",
    "live": false,
    "viewers": 0,
    "thumb": null,
    "updatedAt": "2025-10-16T15:18:11.569Z"
  },
  {
    "slug": "fachitazz",
    "platform": "kick",
    "live": false,
    "viewers": 0,
    "thumb": null,
    "updatedAt": "2025-10-16T15:18:11.687Z"
  },
  {
    "slug": "trotadovzla",
    "platform": "kick",
    "live": false,
    "viewers": 0,
    "thumb": null,
    "updatedAt": "2025-10-16T15:18:11.827Z"
  },
  {
    "slug": "viasuss",
    "platform": "kick",
    "live": false,
    "viewers": 0,
    "thumb": null,
    "updatedAt": "2025-10-16T15:18:12.093Z"
  },
  {
    "slug": "bressser",
    "platform": "kick",
    "live": false,
    "viewers": 0,
    "thumb": null,
    "updatedAt": "2025-10-16T15:18:12.197Z"
  },
  {
    "slug": "leiluchy",
    "platform": "kick",
    "live": false,
    "viewers": 0,
    "thumb": null,
    "updatedAt": "2025-10-16T15:18:12.202Z"
  },
  {
    "slug": "icarito0o",
    "platform": "kick",
    "live": false,
    "viewers": 0,
    "thumb": null,
    "updatedAt": "2025-10-16T15:18:12.213Z"
  },
  {
    "slug": "gangii",
    "platform": "kick",
    "live": false,
    "viewers": 0,
    "thumb": null,
    "updatedAt": "2025-10-16T15:18:12.432Z"
  },
  {
    "slug": "magmaparalasnenas",
    "platform": "kick",
    "live": false,
    "viewers": 0,
    "thumb": null,
    "updatedAt": "2025-10-16T15:18:12.699Z"
  }
]