[
  {
    "slug": "ciro",
    "platform": "kick",
    "live": false,
    "viewers": 0,
    "thumb": null,
    "updatedAt": "2025-10-26T20:21:20.452Z"
  },
  {
    "slug": "ogsantiago",
    "platform": "kick",
    "live": false,
    "viewers": 0,
    "thumb": null,
    "updatedAt": "2025-10-26T20:21:20.453Z"
  },
  {
    "slug": "jwaken",
    "platform": "kick",
    "live": false,
    "viewers": 0,
    "thumb": null,
    "updatedAt": "2025-10-26T20:21:20.454Z"
  },
  {
    "slug": "exequiel",
    "platform": "kick",
    "live": false,
    "viewers": 0,
    "thumb": null,
    "updatedAt": "2025-10-26T20:21:20.455Z"
  },
  {
    "slug": "cotoov",
    "platform": "kick",
    "live": false,
    "viewers": 0,
    "thumb": null,
    "updatedAt": "2025-10-26T20:21:20.559Z"
  },
  {
    "slug": "jeyciiv",
    "platform": "kick",
    "live": false,
    "viewers": 0,
    "thumb": null,
    "updatedAt": "2025-10-26T20:21:20.751Z"
  },
  {
    "slug": "yxnsi",
    "platform": "kick",
    "live": false,
    "viewers": 0,
    "thumb": null,
    "updatedAt": "2025-10-26T20:21:20.861Z"
  },
  {
    "slug": "maiston",
    "platform": "kick",
    "live": false,
    "viewers": 0,
    "thumb": null,
    "updatedAt": "2025-10-26T20:21:21.063Z"
  },
  {
    "slug": "zerok",
    "platform": "kick",
    "live": false,
    "viewers": 0,
    "thumb": null,
    "updatedAt": "2025-10-26T20:21:21.077Z"
  },
  {
    "slug": "tatog2",
    "platform": "kick",
    "live": false,
    "viewers": 0,
    "thumb": null,
    "updatedAt": "2025-10-26T20:21:21.094Z"
  },
  {
    "slug": "peppalex",
    "platform": "kick",
    "live": false,
    "viewers": 0,
    "thumb": null,
    "updatedAt": "2025-10-26T20:21:21.212Z"
  },
  {
    "slug": "joeelvzla",
    "platform": "kick",
    "live": false,
    "viewers": 0,
    "thumb": null,
    "updatedAt": "2025-10-26T20:21:21.442Z"
  },
  {
    "slug": "fachitazz",
    "platform": "kick",
    "live": false,
    "viewers": 0,
    "thumb": null,
    "updatedAt": "2025-10-26T20:21:21.456Z"
  },
  {
    "slug": "ignaa",
    "platform": "kick",
    "live": false,
    "viewers": 0,
    "thumb": null,
    "updatedAt": "2025-10-26T20:21:21.502Z"
  },
  {
    "slug": "leiluchy",
    "platform": "kick",
    "live": false,
    "viewers": 0,
    "thumb": null,
    "updatedAt": "2025-10-26T20:21:21.525Z"
  },
  {
    "slug": "viasuss",
    "platform": "kick",
    "live": false,
    "viewers": 0,
    "thumb": null,
    "updatedAt": "2025-10-26T20:21:21.682Z"
  },
  {
    "slug": "icarito0o",
    "platform": "kick",
    "live": false,
    "viewers": 0,
    "thumb": null,
    "updatedAt": "2025-10-26T20:21:21.825Z"
  },
  {
    "slug": "bressser",
    "platform": "kick",
    "live": false,
    "viewers": 0,
    "thumb": null,
    "updatedAt": "2025-10-26T20:21:21.997Z"
  },
  {
    "slug": "trotadovzla",
    "platform": "kick",
    "live": false,
    "viewers": 0,
    "thumb": null,
    "updatedAt": "2025-10-26T20:21:22.056Z"
  },
  {
    "slug": "gangii",
    "platform": "kick",
    "live": false,
    "viewers": 0,
    "thumb": null,
    "updatedAt": "2025-10-26T20:21:22.067Z"
  },
  {
    "slug": "magmaparalasnenas",
    "platform": "kick",
    "live": false,
    "viewers": 0,
    "thumb": null,
    "updatedAt": "2025-10-26T20:21:22.289Z"
  }
]