[
  {
    "slug": "cotoov",
    "platform": "kick",
    "live": false,
    "viewers": 0,
    "thumb": null,
    "updatedAt": "2026-05-03T21:38:32.584Z",
    "error": "HTTP 403"
  },
  {
    "slug": "jwaken",
    "platform": "kick",
    "live": false,
    "viewers": 0,
    "thumb": null,
    "updatedAt": "2026-05-03T21:38:32.586Z",
    "error": "HTTP 403"
  },
  {
    "slug": "exequiel",
    "platform": "kick",
    "live": false,
    "viewers": 0,
    "thumb": null,
    "updatedAt": "2026-05-03T21:38:32.589Z",
    "error": "HTTP 403"
  },
  {
    "slug": "ogsantiago",
    "platform": "kick",
    "live": false,
    "viewers": 0,
    "thumb": null,
    "updatedAt": "2026-05-03T21:38:32.592Z",
    "error": "HTTP 403"
  },
  {
    "slug": "ciro",
    "platform": "kick",
    "live": false,
    "viewers": 0,
    "thumb": null,
    "updatedAt": "2026-05-03T21:38:32.603Z",
    "error": "HTTP 403"
  },
  {
    "slug": "zerok",
    "platform": "kick",
    "live": false,
    "viewers": 0,
    "thumb": null,
    "updatedAt": "2026-05-03T21:38:34.403Z",
    "error": "HTTP 403"
  },
  {
    "slug": "yxnsi",
    "platform": "kick",
    "live": false,
    "viewers": 0,
    "thumb": null,
    "updatedAt": "2026-05-03T21:38:34.405Z",
    "error": "HTTP 403"
  },
  {
    "slug": "tatog2",
    "platform": "kick",
    "live": false,
    "viewers": 0,
    "thumb": null,
    "updatedAt": "2026-05-03T21:38:34.406Z",
    "error": "HTTP 403"
  },
  {
    "slug": "jeyciiv",
    "platform": "kick",
    "live": false,
    "viewers": 0,
    "thumb": null,
    "updatedAt": "2026-05-03T21:38:34.410Z",
    "error": "HTTP 403"
  },
  {
    "slug": "peppalex",
    "platform": "kick",
    "live": false,
    "viewers": 0,
    "thumb": null,
    "updatedAt": "2026-05-03T21:38:34.420Z",
    "error": "HTTP 403"
  },
  {
    "slug": "maiston",
    "platform": "kick",
    "live": false,
    "viewers": 0,
    "thumb": null,
    "updatedAt": "2026-05-03T21:38:36.221Z",
    "error": "HTTP 403"
  },
  {
    "slug": "fachitazz",
    "platform": "kick",
    "live": false,
    "viewers": 0,
    "thumb": null,
    "updatedAt": "2026-05-03T21:38:36.223Z",
    "error": "HTTP 403"
  },
  {
    "slug": "joeelvzla",
    "platform": "kick",
    "live": false,
    "viewers": 0,
    "thumb": null,
    "updatedAt": "2026-05-03T21:38:36.226Z",
    "error": "HTTP 403"
  },
  {
    "slug": "ignaa",
    "platform": "kick",
    "live": false,
    "viewers": 0,
    "thumb": null,
    "updatedAt": "2026-05-03T21:38:36.232Z",
    "error": "HTTP 403"
  },
  {
    "slug": "viasuss",
    "platform": "kick",
    "live": false,
    "viewers": 0,
    "thumb": null,
    "updatedAt": "2026-05-03T21:38:36.233Z",
    "error": "HTTP 403"
  },
  {
    "slug": "leiluchy",
    "platform": "kick",
    "live": false,
    "viewers": 0,
    "thumb": null,
    "updatedAt": "2026-05-03T21:38:38.038Z",
    "error": "HTTP 403"
  },
  {
    "slug": "trotadovzla",
    "platform": "kick",
    "live": false,
    "viewers": 0,
    "thumb": null,
    "updatedAt": "2026-05-03T21:38:38.038Z",
    "error": "HTTP 403"
  },
  {
    "slug": "bressser",
    "platform": "kick",
    "live": false,
    "viewers": 0,
    "thumb": null,
    "updatedAt": "2026-05-03T21:38:38.040Z",
    "error": "HTTP 403"
  },
  {
    "slug": "gangii",
    "platform": "kick",
    "live": false,
    "viewers": 0,
    "thumb": null,
    "updatedAt": "2026-05-03T21:38:38.046Z",
    "error": "HTTP 403"
  },
  {
    "slug": "icarito0o",
    "platform": "kick",
    "live": false,
    "viewers": 0,
    "thumb": null,
    "updatedAt": "2026-05-03T21:38:38.046Z",
    "error": "HTTP 403"
  },
  {
    "slug": "magmaparalasnenas",
    "platform": "kick",
    "live": false,
    "viewers": 0,
    "thumb": null,
    "updatedAt": "2026-05-03T21:38:39.855Z",
    "error": "HTTP 403"
  }
]